MANIFEST.in
setup.cfg
setup.py
rdir/__init__.py
rdir/rdir.py
rdir.egg-info/PKG-INFO
rdir.egg-info/SOURCES.txt
rdir.egg-info/dependency_links.txt
rdir.egg-info/requires.txt
rdir.egg-info/top_level.txt
rdir/core/__init__.py
rdir/core/rdir_core.py
rdir/core/rdir_node.py
rdir/generateHTML/__init__.py
rdir/generateHTML/generate_page.py
rdir/generateHTML/bin/jquery.min.js
rdir/generateHTML/bin/rdir_tree.js
rdir/generateHTML/template/tree_node_template.html
rdir/generateHTML/template/tree_template.html