Metadata-Version: 1.0
Name: rdir
Version: 0.52
Summary: More powerful recursive dir. Support HTML pretty view in tree structure.
Home-page: http://www.github.com/Lhfcws/rdir
Author: Lhfcws Wu
Author-email: lhfcws@gmail.com
License: MIT
Keywords: dir,doc,pydoc,html
Platform: UNKNOWN
